oshino_prometheus/__init__.py
oshino_prometheus/agent.py
oshino_prometheus/util.py
oshino_prometheus/version.py
oshino_prometheus-0.1.1.dist-info/DESCRIPTION.rst
oshino_prometheus-0.1.1.dist-info/METADATA
oshino_prometheus-0.1.1.dist-info/RECORD
oshino_prometheus-0.1.1.dist-info/WHEEL
oshino_prometheus-0.1.1.dist-info/metadata.json
oshino_prometheus-0.1.1.dist-info/top_level.txt
