Metadata-Version: 2.0
Name: oshino-prometheus
Version: 0.1.1
Summary: Read metrics from Prometheus
Home-page: UNKNOWN
Author: Šarūnas Navickas
Author-email: zaibacu@gmail.com
License: UNKNOWN
Platform: UNKNOWN
Requires-Dist: oshino
